{"updated": 1615442805, "data": [{"1": [{"name": "Leno", "points": -1, "team": "ARS", "id": "8"}], "2": [{"name": "Bednarek", "points": -7, "team": "SOU", "id": "376"}, {"name": "David Luiz", "points": -3, "team": "ARS", "id": "3"}, {"name": "Ramsay", "points": -3, "team": "SOU", "id": "598"}, {"name": "Stephens", "points": -3, "team": "SOU", "id": "367"}, {"name": "Bertrand", "points": -2, "team": "SOU", "id": "362"}], "3": [{"name": "Jankewitz", "points": -2, "team": "SOU", "id": "643"}, {"name": "Stephens", "points": 0, "team": "BUR", "id": "55"}, {"name": "Kant\u00e9", "points": 0, "team": "CHE", "id": "113"}, {"name": "Mendy", "points": 0, "team": "LEI", "id": "518"}], "4": [{"name": "Mumbongo", "points": 0, "team": "BUR", "id": "613"}], "total": -21}, {"1": [], "2": [], "3": [{"name": "van de Beek", "points": 0, "team": "MUN", "id": "495"}, {"name": "Pulisic", "points": 0, "team": "CHE", "id": "119"}, {"name": "Cavaleiro", "points": 0, "team": "FUL", "id": "187"}], "4": []}], "completed": true, "gameweek": 22}