{"updated": 1615443220, "data": [{"1": [{"name": "Meslier", "points": 0, "team": "LEE", "id": "213"}], "2": [{"name": "Alioski", "points": -1, "team": "LEE", "id": "201"}, {"name": "Dallas", "points": -1, "team": "LEE", "id": "200"}, {"name": "Davies", "points": 0, "team": "TOT", "id": "395"}, {"name": "Kabak", "points": 0, "team": "LIV", "id": "652"}, {"name": "Cooper", "points": 0, "team": "LEE", "id": "195"}], "3": [{"name": "Sanson", "points": 0, "team": "AVL", "id": "647"}, {"name": "Onomah", "points": 0, "team": "FUL", "id": "188"}, {"name": "Choudhury", "points": 1, "team": "LEI", "id": "234"}], "4": [{"name": "Fabio Silva", "points": 1, "team": "WOL", "id": "504"}, {"name": "Adams", "points": 1, "team": "SOU", "id": "377"}], "total": 1}, {"1": [], "2": [{"name": "Bednarek", "points": 0, "team": "SOU", "id": "376"}, {"name": "Dier", "points": 0, "team": "TOT", "id": "391"}, {"name": "Ayling", "points": 0, "team": "LEE", "id": "197"}, {"name": "Basham", "points": 0, "team": "SHU", "id": "345"}], "3": [{"name": "Greenwood", "points": 1, "team": "MUN", "id": "315"}, {"name": "van de Beek", "points": 1, "team": "MUN", "id": "495"}, {"name": "P\u00e9rez", "points": 1, "team": "LEI", "id": "229"}, {"name": "Noble", "points": 1, "team": "WHU", "id": "427"}, {"name": "Livermore", "points": 1, "team": "WBA", "id": "409"}, {"name": "Bale", "points": 1, "team": "TOT", "id": "543"}, {"name": "Snodgrass", "points": 1, "team": "WBA", "id": "428"}, {"name": "Fraser", "points": 1, "team": "NEW", "id": "507"}, {"name": "Townsend", "points": 1, "team": "CRY", "id": "137"}, {"name": "Elneny", "points": 1, "team": "ARS", "id": "526"}, {"name": "Tr\u00e9z\u00e9guet", "points": 1, "team": "AVL", "id": "40"}, {"name": "Lallana", "points": 1, "team": "BHA", "id": "54"}, {"name": "Lundstram", "points": 1, "team": "SHU", "id": "355"}, {"name": "Chamberlain", "points": 1, "team": "LIV", "id": "248"}, {"name": "Harrison", "points": 1, "team": "LEE", "id": "203"}, {"name": "Klich", "points": 1, "team": "LEE", "id": "198"}, {"name": "Alli", "points": 1, "team": "TOT", "id": "394"}, {"name": "Willian", "points": 1, "team": "ARS", "id": "478"}, {"name": "Mendy", "points": 1, "team": "LEI", "id": "518"}, {"name": "Phillips", "points": 1, "team": "WBA", "id": "411"}, {"name": "Brownhill", "points": 1, "team": "BUR", "id": "98"}, {"name": "Milner", "points": 1, "team": "LIV", "id": "241"}, {"name": "Lucas Moura", "points": 1, "team": "TOT", "id": "392"}, {"name": "Shaqiri", "points": 1, "team": "LIV", "id": "247"}, {"name": "Bernard", "points": 1, "team": "EVE", "id": "154"}, {"name": "Oriol Romeu", "points": 1, "team": "SOU", "id": "364"}, {"name": "Torres", "points": 1, "team": "MCI", "id": "287"}, {"name": "Djenepo", "points": 1, "team": "SOU", "id": "382"}, {"name": "Brady", "points": 1, "team": "BUR", "id": "95"}, {"name": "De Bruyne", "points": 1, "team": "MCI", "id": "272"}, {"name": "Lamela", "points": 1, "team": "TOT", "id": "387"}, {"name": "Sissoko", "points": 1, "team": "TOT", "id": "385"}, {"name": "Kant\u00e9", "points": 1, "team": "CHE", "id": "113"}], "4": [{"name": "McBurnie", "points": 1, "team": "SHU", "id": "357"}, {"name": "Mateta", "points": 1, "team": "CRY", "id": "641"}, {"name": "Carroll", "points": 1, "team": "NEW", "id": "320"}, {"name": "Abraham", "points": 1, "team": "CHE", "id": "118"}, {"name": "Welbeck", "points": 1, "team": "BHA", "id": "588"}, {"name": "Huggins", "points": 1, "team": "LEE", "id": "619"}, {"name": "Joelinton", "points": 1, "team": "NEW", "id": "340"}]}], "completed": true, "gameweek": 24}